snaketrace/__init__.py
snaketrace/__main__.py
snaketrace/trace.py
snaketrace/tsv.py
snaketrace/tests/__init__.py
snaketrace/tests/test_snaketrace.py
snaketrace-0.3.1.dist-info/LICENSE
snaketrace-0.3.1.dist-info/METADATA
snaketrace-0.3.1.dist-info/WHEEL
snaketrace-0.3.1.dist-info/entry_points.txt
snaketrace-0.3.1.dist-info/top_level.txt
snaketrace-0.3.1.dist-info/RECORD
