Metadata-Version: 2.1
Name: snaketrace
Version: 0.3.1
Summary: An strace-like tool for Python audit events
Home-page: https://github.com/dcoles/snaketrace
License: UNKNOWN
Platform: UNKNOWN
Classifier: Programming Language :: Python :: 3
Classifier: Programming Language :: Python :: 3.8
Classifier: License :: OSI Approved :: MIT License
Classifier: Operating System :: OS Independent
Requires-Python: >=3.8
